pith_cli/__init__.py
pith_cli/__main__.py
pith_cli/analyze.py
pith_cli/capture.py
pith_cli/cli.py
pith_cli/config.py
pith_cli/diff.py
pith_cli/heuristic.py
pith_cli/platforms.py
pith_cli/py.typed
pith_cli/query.py
pith_cli/providers/__init__.py
pith_cli/providers/anthropic.py
pith_cli/providers/base.py
pith_cli/providers/none.py
pith_cli/providers/ollama.py
pith_cli/providers/openai.py
pith_cli/wrappers/__init__.py
pith_cli/wrappers/base.py
pith_cli/wrappers/bash.py
pith_cli/wrappers/cmd.py
pith_cli/wrappers/powershell.py
pypith_cli-0.1.2.dist-info/METADATA
pypith_cli-0.1.2.dist-info/WHEEL
pypith_cli-0.1.2.dist-info/entry_points.txt
pypith_cli-0.1.2.dist-info/RECORD
