Metadata-Version: 2.4
Name: pypith-cli
Version: 0.1.2
Summary: Wrap any CLI with agent-friendly progressive discovery
Project-URL: Homepage, https://github.com/ThomasRohde/pith
Project-URL: Repository, https://github.com/ThomasRohde/pith
Project-URL: Documentation, https://github.com/ThomasRohde/pith#readme
Project-URL: Changelog, https://github.com/ThomasRohde/pith/releases
Author-email: Thomas Klok Rohde <rohde.thomas@gmail.com>
License-Expression: MIT
Keywords: agent,ai,cli,command-line,llm,progressive-discovery,wrapper
Classifier: Development Status :: 3 - Alpha
Classifier: Environment :: Console
Classifier: Intended Audience :: Developers
Classifier: License :: OSI Approved :: MIT License
Classifier: Programming Language :: Python :: 3
Classifier: Programming Language :: Python :: 3.10
Classifier: Programming Language :: Python :: 3.11
Classifier: Programming Language :: Python :: 3.12
Classifier: Programming Language :: Python :: 3.13
Classifier: Topic :: Software Development :: Libraries :: Python Modules
Classifier: Topic :: System :: Shells
Classifier: Typing :: Typed
Requires-Python: >=3.10
Requires-Dist: anthropic>=0.75.0
Requires-Dist: click>=8.0
Requires-Dist: pypith>=0.1.0
Requires-Dist: pyyaml>=6.0
Provides-Extra: all
Requires-Dist: anthropic>=0.18; extra == 'all'
Requires-Dist: ollama>=0.1; extra == 'all'
Requires-Dist: openai>=1.0; extra == 'all'
Provides-Extra: anthropic
Requires-Dist: anthropic>=0.18; extra == 'anthropic'
Provides-Extra: llm
Requires-Dist: anthropic>=0.75.0; extra == 'llm'
Requires-Dist: ollama>=0.6.1; extra == 'llm'
Requires-Dist: openai>=2.8.1; extra == 'llm'
Provides-Extra: ollama
Requires-Dist: ollama>=0.1; extra == 'ollama'
Provides-Extra: openai
Requires-Dist: openai>=1.0; extra == 'openai'
